TorturePhrases_Estimator/__init__.py
TorturePhrases_Estimator/torture_phrases.py
TorturePhrases_Estimator/tortured_phrases_list.txt
TorturePhrases_Estimator-4.0.dist-info/METADATA
TorturePhrases_Estimator-4.0.dist-info/WHEEL
TorturePhrases_Estimator-4.0.dist-info/top_level.txt
TorturePhrases_Estimator-4.0.dist-info/RECORD
