Metadata-Version: 2.1
Name: TorturePhrases_Estimator
Version: 4.0
Summary: A Python package to identify tortured phrases in text
Home-page: https://github.com/Usman761/TorturePhrases_Estimator
Author: Usman
Author-email: usman.alot761@gmail.com
Classifier: Programming Language :: Python :: 3
Classifier: License :: OSI Approved :: MIT License
Classifier: Operating System :: OS Independent
